adbctool/__init__.py
adbctool/extract_dbc_meta.py
adbctool/gen.py
adbctool/gen_proto_file.py
adbctool/gen_protocols.py
adbctool/gen_vehicle_controller_and_manager.py
adbctool/template/control_protocol.cc.tpl
adbctool/template/control_protocol.h.tpl
adbctool/template/controller.cc.tpl
adbctool/template/controller.h.tpl
adbctool/template/controller_manager_BUILD.tpl
adbctool/template/message_manager.cc.tpl
adbctool/template/message_manager.h.tpl
adbctool/template/protocol_BUILD.tpl
adbctool/template/report_protocol.cc.tpl
adbctool/template/report_protocol.h.tpl
adbctool/template/vehicle_factory.cc.tpl
adbctool/template/vehicle_factory.h.tpl
adbctool-0.1.5.dist-info/licenses/LICENSE
adbctool-0.1.5.dist-info/METADATA
adbctool-0.1.5.dist-info/WHEEL
adbctool-0.1.5.dist-info/entry_points.txt
adbctool-0.1.5.dist-info/top_level.txt
adbctool-0.1.5.dist-info/RECORD
