Metadata-Version: 2.4
Name: adbctool
Version: 0.1.5
Summary: apollo dbc tool
Author-email: daohu527 <daohu527@gmail.com>
License-Expression: Apache-2.0
Project-URL: Homepage, https://github.com/daohu527/adbctool
Project-URL: BugTracker, https://github.com/daohu527/adbctool/issues
Classifier: Programming Language :: Python :: 3
Classifier: Operating System :: OS Independent
Requires-Python: >=3.6
License-File: LICENSE
Requires-Dist: pyyaml
Requires-Dist: chardet
Dynamic: license-file
